etcd3gw/__init__.py
etcd3gw/client.py
etcd3gw/exceptions.py
etcd3gw/lease.py
etcd3gw/lock.py
etcd3gw/utils.py
etcd3gw/watch.py
etcd3gw/examples/__init__.py
etcd3gw/examples/etcd.py
etcd3gw/examples/watcher.py
etcd3gw/tests/__init__.py
etcd3gw/tests/base.py
etcd3gw/tests/test_client.py
etcd3gw/tests/test_etcd3gw.py
etcd3gw-2.5.0.dist-info/licenses/AUTHORS
etcd3gw-2.5.0.dist-info/licenses/LICENSE
etcd3gw-2.5.0.dist-info/METADATA
etcd3gw-2.5.0.dist-info/WHEEL
etcd3gw-2.5.0.dist-info/pbr.json
etcd3gw-2.5.0.dist-info/top_level.txt
etcd3gw-2.5.0.dist-info/RECORD
